sheet_orm/__init__.py
sheet_orm-0.1.0.dist-info/LICENSE
sheet_orm-0.1.0.dist-info/WHEEL
sheet_orm-0.1.0.dist-info/METADATA
sheet_orm-0.1.0.dist-info/RECORD
